dangerously_prompt_permissions/__init__.py
dangerously_prompt_permissions/manager.py
dangerously_prompt_permissions/py.typed
dangerously_prompt_permissions-0.1.0.dist-info/METADATA
dangerously_prompt_permissions-0.1.0.dist-info/WHEEL
dangerously_prompt_permissions-0.1.0.dist-info/licenses/LICENSE
dangerously_prompt_permissions-0.1.0.dist-info/RECORD
