Metadata-Version: 2.4
Name: dangerously-prompt-permissions
Version: 0.1.0
Summary: A manager system for Claude Code that intercepts and supervises tool actions using OpenRouter LLMs
Project-URL: Homepage, https://github.com/smarsx/dangerously-prompt-permissions
Project-URL: Documentation, https://github.com/smarsx/dangerously-prompt-permissions#readme
Project-URL: Repository, https://github.com/smasrx/dangerously-prompt-permissions
Project-URL: Issues, https://github.com/smarsx/dangerously-prompt-permissions/issues
Author: smarsx
License: MIT
License-File: LICENSE
Keywords: agent,claude,claude-code,hooks,llm,openrouter,permissions,supervisor
Classifier: Development Status :: 3 - Alpha
Classifier: Intended Audience :: Developers
Classifier: License :: OSI Approved :: MIT License
Classifier: Programming Language :: Python :: 3
Classifier: Programming Language :: Python :: 3.10
Classifier: Programming Language :: Python :: 3.11
Classifier: Programming Language :: Python :: 3.12
Classifier: Topic :: Scientific/Engineering :: Artificial Intelligence
Classifier: Topic :: Software Development :: Libraries :: Python Modules
Requires-Python: >=3.10
Requires-Dist: claude-agent-sdk>=0.1.0
Requires-Dist: httpx>=0.25.0
Requires-Dist: orjson>=3.9.0
Requires-Dist: rich>=13.0.0
